[
  {
    "id": 1,
    "category": "Διοίκηση Επιχειρήσεων και Οργανισμών",
    "question": "Η Διοικητική Επιστήμη ως επιστημονικός κλάδος συνδέεται με:",
    "options": {
      "α": "Τη Νομική Επιστήμη",
      "β": "Την Οικονομική Επιστήμη",
      "γ": "Την Κοινωνιολογία",
      "δ": "Όλες τις λοιπές επιστήμες"
    },
    "correct_answer": "δ"
  },
  {
    "id": 2,
    "category": "Διοίκηση Επιχειρήσεων και Οργανισμών",
    "question": "Σε μια εφοδιαστική αλυσίδα υφίσταται:",
    "options": {
      "α": "Ροή πληροφοριών",
      "β": "Ροή προϊόντων",
      "γ": "Ροή κεφαλαίου και γνώσης",
      "δ": "Όλες οι λοιπές απαντήσεις"
    },
    "correct_answer": "δ"
  },
  {
    "id": 3,
    "category": "Διοίκηση Επιχειρήσεων και Οργανισμών",
    "question": "Η ευθύνη για τη διενέργεια ορισμένης λειτουργίας:",
    "options": {
      "α": "Δεν προϋποθέτει την ύπαρξη της αναγκαίας αρμοδιότητας για την εκτέλεσή της",
      "β": "Μόνο σε συγκεκριμένες περιπτώσεις προϋποθέτει την ύπαρξη της αναγκαίας αρμοδιότητας για την εκτέλεσή της",
      "γ": "Προϋποθέτει την ύπαρξη της αναγκαίας αρμοδιότητας για την εκτέλεσή της",
      "δ": "Συνήθως προϋποθέτει την ύπαρξη της αναγκαίας αρμοδιότητας για την εκτέλεσή της"
    },
    "correct_answer": "γ"
  },
  {
    "id": 4,
    "category": "Διοίκηση Επιχειρήσεων και Οργανισμών",
    "question": "Ποιος είναι ο βασικός στόχος του στρατηγικού μάνατζμεντ;",
    "options": {
      "α": "Η βελτιστοποίηση βραχυπρόθεσμων αποτελεσμάτων",
      "β": "Η λειτουργική αποδοτικότητα μέσω ελέγχου κόστους",
      "γ": "Η προσαρμογή στις τρέχουσες οργανωσιακές απαιτήσεις",
      "δ": "Η δημιουργία και διατήρηση ανταγωνιστικού πλεονεκτήματος"
    },
    "correct_answer": "δ"
  },
  {
    "id": 5,
    "category": "Διοίκηση Επιχειρήσεων και Οργανισμών",
    "question": "Ποιο στοιχείο ΔΕΝ περιλαμβάνεται στις πέντε ανταγωνιστικές δυνάμεις του M. Porter;",
    "options": {
      "α": "Η απειλή υποκατάστατων προϊόντων",
      "β": "Η διαπραγματευτική δύναμη των προμηθευτών",
      "γ": "Η τεχνολογική καινοτομία του κλάδου",
      "δ": "Η ένταση του ανταγωνισμού μεταξύ υφιστάμενων οργανισμών"
    },
    "correct_answer": "γ"
  },
  {
    "id": 6,
    "category": "Διοίκηση Επιχειρήσεων και Οργανισμών",
    "question": "Ποιο χαρακτηριστικό ΔΕΝ συνάδει με τη στρατηγική διαφοροποίησης του Μ. Porter;",
    "options": {
      "α": "Η έμφαση στην ποιότητα του προϊόντος ή της υπηρεσίας",
      "β": "Ο ανταγωνισμός αποκλειστικά μέσω χαμηλού κόστους",
      "γ": "Η δημιουργία ισχυρής επωνυμίας",
      "δ": "Η καινοτομία προϊόντος ή υπηρεσίας"
    },
    "correct_answer": "β"
  },
  {
    "id": 7,
    "category": "Διοίκηση Επιχειρήσεων και Οργανισμών",
    "question": "Στη δημόσια διοίκηση, η αποτελεσματικότητα μετράται κυρίως με βάση:",
    "options": {
      "α": "Την κερδοφορία",
      "β": "Την επίτευξη δημόσιας αξίας και κοινωνικών στόχων",
      "γ": "Τη μείωση προσωπικού και διοικητικού κόστους",
      "δ": "Την ιδιωτικοποίηση υπηρεσιών"
    },
    "correct_answer": "β"
  },
  {
    "id": 8,
    "category": "Διοίκηση Επιχειρήσεων και Οργανισμών",
    "question": "Η αποτελεσματικότητα ενός οργανισμού είναι:",
    "options": {
      "α": "Τα κόστη του οργανισμού για την επίτευξη ενός αποτελέσματος",
      "β": "Ο βαθμός στον οποίο ο οργανισμός επιτυγχάνει τους στόχους του",
      "γ": "Συνώνυμη της αποδοτικότητας του οργανισμού",
      "δ": "Το κλάσμα με αριθμητή το πραγματοποιηθέν αποτέλεσμα (εκροή) και παρονομαστή τα κόστη που έγιναν για την πραγματοποίηση του αποτελέσματος (εισροές)"
    },
    "correct_answer": "β"
  },
  {
    "id": 9,
    "category": "Διοίκηση Επιχειρήσεων και Οργανισμών",
    "question": "Ποιο από τα παρακάτω αποτελεί θεμελιώδες και διαχρονικό γνώρισμα της δημόσιας διοίκησης;",
    "options": {
      "α": "Η αποδοτικότητα με όρους αγοράς",
      "β": "Η λογοδοσία και η διαφάνεια",
      "γ": "Ο ανταγωνισμός μεταξύ των παρόχων υπηρεσιών",
      "δ": "Η μέγιστη οικονομική απόδοση"
    },
    "correct_answer": "β"
  },
  {
    "id": 10,
    "category": "Διοίκηση Επιχειρήσεων και Οργανισμών",
    "question": "Τι στόχο έχει η Λιτή Διοίκηση (Lean Management);",
    "options": {
      "α": "Την αύξηση των ελέγχων",
      "β": "Την εντατικοποίηση της εργασίας",
      "γ": "Την ελαχιστοποίηση της σπατάλης και τη μεγιστοποίηση της αξίας",
      "δ": "Την τυποποίηση χωρίς ευελιξία και καινοτομία"
    },
    "correct_answer": "γ"
  },
  {
    "id": 11,
    "category": "Διοίκηση Επιχειρήσεων και Οργανισμών",
    "question": "Ποιο χαρακτηριστικό διαφοροποιεί τον στρατηγικό από τον λειτουργικό σχεδιασμό;",
    "options": {
      "α": "Το επίπεδο λεπτομέρειας του σχεδιασμού",
      "β": "Η χρονική διάρκεια του σχεδιασμού",
      "γ": "Ο μακροπρόθεσμος προσανατολισμός",
      "δ": "Η συμμετοχή των εργαζομένων"
    },
    "correct_answer": "γ"
  },
  {
    "id": 12,
    "category": "Διοίκηση Επιχειρήσεων και Οργανισμών",
    "question": "Ποιο στοιχείο ΔΕΝ αποτελεί βασική λειτουργία του μάνατζμεντ;",
    "options": {
      "α": "Ο προγραμματισμός",
      "β": "Η οργάνωση",
      "γ": "Η καινοτομία",
      "δ": "Ο έλεγχος"
    },
    "correct_answer": "γ"
  },
  {
    "id": 13,
    "category": "Διοίκηση Επιχειρήσεων και Οργανισμών",
    "question": "Ο προγραμματισμός είναι η διαδικασία:",
    "options": {
      "α": "Μέτρησης αποτελεσμάτων",
      "β": "Θέσπισης στόχων",
      "γ": "Ανάπτυξης προτάσεων για το μέλλον",
      "δ": "Μέτρησης της απόδοσης του παρελθόντος"
    },
    "correct_answer": "γ"
  },
  {
    "id": 14,
    "category": "Διοίκηση Επιχειρήσεων και Οργανισμών",
    "question": "Η ποσοτική έκφραση των σκοπών-στόχων ενός οργανισμού είναι χαρακτηριστικό της λειτουργίας:",
    "options": {
      "α": "Της ηγεσίας",
      "β": "Του προγραμματισμού",
      "γ": "Του ελέγχου",
      "δ": "Του προϋπολογισμού"
    },
    "correct_answer": "β"
  },
  {
    "id": 15,
    "category": "Διοίκηση Επιχειρήσεων και Οργανισμών",
    "question": "Ποια λειτουργία του μάνατζμεντ απαντά πρωτίστως στο ερώτημα «τι πρέπει να γίνει και γιατί»;",
    "options": {
      "α": "Η οργάνωση",
      "β": "Η ηγεσία",
      "γ": "Ο έλεγχος",
      "δ": "Ο προγραμματισμός"
    },
    "correct_answer": "δ"
  },
  {
    "id": 16,
    "category": "Διοίκηση Επιχειρήσεων και Οργανισμών",
    "question": "Σε ποια λειτουργία του μάνατζμεντ εντάσσεται πρωτίστως ο καθορισμός στόχων;",
    "options": {
      "α": "Στην οργάνωση",
      "β": "Στη διεύθυνση",
      "γ": "Στον έλεγχο",
      "δ": "Στον προγραμματισμό"
    },
    "correct_answer": "δ"
  },
  {
    "id": 17,
    "category": "Διοίκηση Επιχειρήσεων και Οργανισμών",
    "question": "Η στοχοθεσία εντάσσεται στα καθήκοντα ενός διοικητικού στελέχους για:",
    "options": {
      "α": "Προγραμματισμό",
      "β": "Οργάνωση",
      "γ": "Παρακίνηση",
      "δ": "Συντονισμό"
    },
    "correct_answer": "α"
  },
  {
    "id": 18,
    "category": "Διοίκηση Επιχειρήσεων και Οργανισμών",
    "question": "Η Ανάλυση S.W.O.T. (Strengths – Weaknesses - Opportunities – Threats) εκπονείται κατά τη διάρκεια:",
    "options": {
      "α": "Του προγραμματισμού",
      "β": "Της οργάνωσης",
      "γ": "Του συντονισμού",
      "δ": "Του ελέγχου"
    },
    "correct_answer": "α"
  },
  {
    "id": 19,
    "category": "Διοίκηση Επιχειρήσεων και Οργανισμών",
    "question": "«Άρτια εκπαιδευμένο ανθρώπινο δυναμικό ενός οργανισμού». Σε ποιο από τα τέσσερα τεταρτημόρια της S.W.O.T. Ανάλυσης εντάσσεται η συγκεκριμένη πρόταση;",
    "options": {
      "α": "Strengths (Δυνατότητες)",
      "β": "Weaknesses (Αδυναμίες)",
      "γ": "Opportunities (Ευκαιρίες)",
      "δ": "Threats (Απειλές)"
    },
    "correct_answer": "α"
  },
  {
    "id": 20,
    "category": "Διοίκηση Επιχειρήσεων και Οργανισμών",
    "question": "Τι χαρακτηρίζει τη διοίκηση μέσω στόχων (Management By Objectives);",
    "options": {
      "α": "Ο έλεγχος μέσω κανόνων",
      "β": "Ο συμμετοχικός καθορισμός στόχων",
      "γ": "Αποκλειστικά ποιοτικοί στόχοι αποτελεσματικότητας",
      "δ": "Ο κεντρικός σχεδιασμός χωρίς ανατροφοδότηση"
    },
    "correct_answer": "β"
  },
  {
    "id": 21,
    "category": "Διοίκηση Επιχειρήσεων και Οργανισμών",
    "question": "Ποιος είναι ο βασικός σκοπός της διαδικασίας στοχοθεσίας στις δημόσιες υπηρεσίες;",
    "options": {
      "α": "Η τυπική καταγραφή των καθηκόντων κάθε υπαλλήλου, όπως αυτά περιγράφονται στο οργανόγραμμα του φορέα",
      "β": "Η ποσοτική μέτρηση της απόδοσης κάθε υπαλλήλου, με βάση συγκεκριμένους αριθμητικούς δείκτες",
      "γ": "Ο καθορισμός σαφών, μετρήσιμων, εφικτών, σχετικών και χρονικά οριοθετημένων στόχων για κάθε οργανική μονάδα, σε συνάρτηση με το Σχέδιο Δράσης του φορέα",
      "δ": "Η διασφάλιση της ομοιόμορφης κατανομής των εργασιών μεταξύ των υπαλλήλων κάθε οργανικής μονάδας"
    },
    "correct_answer": "γ"
  },
  {
    "id": 22,
    "category": "Διοίκηση Επιχειρήσεων και Οργανισμών",
    "question": "SMART στόχος ενός οργανισμού είναι:",
    "options": {
      "α": "Η μείωση του χρόνου αναμονής των πολιτών για τη διεκπεραίωση του αιτήματός τους εντός πέντε (5) μηνών",
      "β": "Η μείωση του χρόνου αναμονής των πολιτών για τη διεκπεραίωση του αιτήματός τους από δύο (2) ώρες σε μία (1) ώρα",
      "γ": "Η μείωση του χρόνου αναμονής των πολιτών για τη διεκπεραίωση του αιτήματός τους από δύο (2) ώρες σε μία (1) ώρα εντός πέντε (5) μηνών",
      "δ": "Η μείωση του χρόνου αναμονής των πολιτών για τη διεκπεραίωση του αιτήματός τους όσο το δυνατόν πιο σύντομα"
    },
    "correct_answer": "γ"
  },
  {
    "id": 23,
    "category": "Διοίκηση Επιχειρήσεων και Οργανισμών",
    "question": "Ποια λειτουργία του μάνατζμεντ εξασφαλίζει τον συντονισμό ανθρώπων και πόρων;",
    "options": {
      "α": "Ο προγραμματισμός",
      "β": "Η οργάνωση",
      "γ": "Ο έλεγχος",
      "δ": "Η καινοτομία"
    },
    "correct_answer": "β"
  },
  {
    "id": 24,
    "category": "Διοίκηση Επιχειρήσεων και Οργανισμών",
    "question": "Η διαδικασία της οργάνωσης είναι μια διοικητική λειτουργία που αποσκοπεί:",
    "options": {
      "α": "Στην ανάλυση του περιβάλλοντος",
      "β": "Στην πρόβλεψη",
      "γ": "Στην οριοθέτηση των ρόλων και των καθηκόντων των εργαζομένων",
      "δ": "Στην παρακίνηση των εργαζομένων"
    },
    "correct_answer": "γ"
  },
  {
    "id": 25,
    "category": "Διοίκηση Επιχειρήσεων και Οργανισμών",
    "question": "Οι σύγχρονες απόψεις στη θεωρία των οργανώσεων για την αποτελεσματικότερη λειτουργία μιας οργάνωσης, προϋποθέτουν:",
    "options": {
      "α": "Συγκεντρωτισμό των αρμοδιοτήτων",
      "β": "Περιορισμό των ευθυνών των αρμοδίων προσώπων",
      "γ": "Αναφορά κάθε εργαζόμενου/ης σε έναν/μία Προϊστάμενο/η ή συντονιστή/τρια",
      "δ": "Εξατομικευμένη εργασία κάθε εργαζομένου/ης βάσει των προσόντων του/ης"
    },
    "correct_answer": "γ"
  },
  {
    "id": 26,
    "category": "Διοίκηση Επιχειρήσεων και Οργανισμών",
    "question": "Σύμφωνα με τους Τ. Burns and G.M. Stalker ποια μορφή οργανωτικής δομής ευνοεί την καινοτομία;",
    "options": {
      "α": "Η γραμμική",
      "β": "Η γραφειοκρατική",
      "γ": "Η μηχανιστική",
      "δ": "Η οργανική"
    },
    "correct_answer": "δ"
  },
  {
    "id": 27,
    "category": "Διοίκηση Επιχειρήσεων και Οργανισμών",
    "question": "Το οργανόγραμμα:",
    "options": {
      "α": "Απεικονίζει τη διάρθρωση των υπηρεσιών ενός δημόσιου φορέα σε οργανικές μονάδες",
      "β": "Ταυτίζεται με τον οργανισμό ενός δημόσιου φορέα",
      "γ": "Απεικονίζει τη διάρθρωση των υπηρεσιών ενός δημόσιου φορέα σε οργανικές μονάδες και την κατανομή των αρμοδιοτήτων σε καθεμιά από αυτές",
      "δ": "Απεικονίζει την αποστολή ενός δημόσιου φορέα και τη διάρθρωση των υπηρεσιών του σε οργανικές μονάδες"
    },
    "correct_answer": "γ"
  },
  {
    "id": 28,
    "category": "Διοίκηση Επιχειρήσεων και Οργανισμών",
    "question": "Το οργανόγραμμα αποτελεί βασικό συστατικό στοιχείο:",
    "options": {
      "α": "Της ηγεσίας",
      "β": "Του προγραμματισμού",
      "γ": "Της επικοινωνίας",
      "δ": "Της οργάνωσης"
    },
    "correct_answer": "δ"
  },
  {
    "id": 29,
    "category": "Διοίκηση Επιχειρήσεων και Οργανισμών",
    "question": "Ποια δραστηριότητα εντάσσεται κυρίως στη λειτουργία της οργάνωσης;",
    "options": {
      "α": "Ο καθορισμός των στόχων",
      "β": "Η παρακίνηση των εργαζομένων",
      "γ": "Η κατανομή ρόλων και αρμοδιοτήτων",
      "δ": "Η αξιολόγηση των αποτελεσμάτων"
    },
    "correct_answer": "γ"
  },
  {
    "id": 30,
    "category": "Διοίκηση Επιχειρήσεων και Οργανισμών",
    "question": "Ποια λειτουργία του μάνατζμεντ ελέγχει συστηματικά την απόκλιση μεταξύ προγραμματισμένων και πραγματικών ενεργειών;",
    "options": {
      "α": "Ο προγραμματισμός",
      "β": "Η οργάνωση",
      "γ": "Η διεύθυνση",
      "δ": "Ο έλεγχος"
    },
    "correct_answer": "δ"
  },
  {
    "id": 31,
    "category": "Διοίκηση Επιχειρήσεων και Οργανισμών",
    "question": "Ποιο από τα παρακάτω αποτελεί βασικό σφάλμα στη λειτουργία του ελέγχου;",
    "options": {
      "α": "Ο καθορισμός των προτύπων",
      "β": "Η ποσοτικοποίηση της απόδοσης",
      "γ": "Ο έλεγχος χωρίς ανατροφοδότηση",
      "δ": "Οι διορθωτικές ενέργειες"
    },
    "correct_answer": "γ"
  },
  {
    "id": 32,
    "category": "Διοίκηση Επιχειρήσεων και Οργανισμών",
    "question": "Ποια μορφή ελέγχου εστιάζει στα αποτελέσματα;",
    "options": {
      "α": "Ο προληπτικός",
      "β": "Ο διαδικαστικός",
      "γ": "Ο απολογιστικός",
      "δ": "Ο γραφειοκρατικός"
    },
    "correct_answer": "γ"
  },
  {
    "id": 33,
    "category": "Διοίκηση Επιχειρήσεων και Οργανισμών",
    "question": "Ποια σχέση συνδέει τον έλεγχο με τον σχεδιασμό;",
    "options": {
      "α": "Είναι ανεξάρτητες λειτουργίες",
      "β": "Ο έλεγχος προηγείται πάντα του σχεδιασμού",
      "γ": "Ο έλεγχος τροφοδοτεί τον επόμενο σχεδιασμό",
      "δ": "Ο σχεδιασμός ακυρώνει τον έλεγχο"
    },
    "correct_answer": "γ"
  },
  {
    "id": 34,
    "category": "Διοίκηση Επιχειρήσεων και Οργανισμών",
    "question": "Όταν ένα διοικητικό στέλεχος εξουσιοδοτεί, η ευθύνη για την εκπλήρωση του καθήκοντος:",
    "options": {
      "α": "Μεταφέρεται πλήρως στους/στις υφιστάμενους/ες",
      "β": "Μοιράζεται μεταξύ υφισταμένων και Προϊσταμένου/ης",
      "γ": "Παραμένει στο στέλεχος (Προϊστάμενο/η)",
      "δ": "Απαλλάσσει πλήρως τον/την Προϊστάμενο/η"
    },
    "correct_answer": "γ"
  },
  {
    "id": 35,
    "category": "Διοίκηση Επιχειρήσεων και Οργανισμών",
    "question": "Στη λήψη στρατηγικών αποφάσεων ένα διοικητικό στέλεχος λαμβάνει υπόψη:",
    "options": {
      "α": "Το εσωτερικό περιβάλλον του οργανισμού",
      "β": "Το εξωτερικό περιβάλλον του οργανισμού",
      "γ": "Και τα δύο είδη περιβάλλοντος",
      "δ": "Κινείται και αποφασίζει με βάση τις προσωπικές του γνώσεις και εμπειρίες"
    },
    "correct_answer": "γ"
  },
  {
    "id": 36,
    "category": "Διοίκηση Επιχειρήσεων και Οργανισμών",
    "question": "Ποιο από τα παρακάτω αποτελεί σύνηθες σφάλμα κατά τη διάρκεια της λήψης αποφάσεων:",
    "options": {
      "α": "Η άμεση ικανοποίηση",
      "β": "Η επιλεκτική αντίληψη",
      "γ": "Η ιδιοτέλεια",
      "δ": "Όλες οι λοιπές απαντήσεις"
    },
    "correct_answer": "δ"
  },
  {
    "id": 37,
    "category": "Διοίκηση Επιχειρήσεων και Οργανισμών",
    "question": "Ποια βήματα περιλαμβάνει η διαδικασία λήψης αποφάσεων;",
    "options": {
      "α": "Εντοπισμό του προβλήματος - ανάπτυξη και αξιολόγηση εναλλακτικών λύσεων- υλοποίηση της απόφασης",
      "β": "Συγκέντρωση εναλλακτικών λύσεων-αξιολόγηση εναλλακτικών λύσεων-επιλογή βέλτιστης λύσης",
      "γ": "Εντοπισμό του προβλήματος-ανάπτυξη, ανάλυση και αξιολόγηση εναλλακτικών λύσεων-υλοποίηση της απόφασης",
      "δ": "Διαπίστωση προβλήματος ή ευκαιρίας- συζήτηση με τα μέλη της ομάδας- υλοποίηση απόφασης"
    },
    "correct_answer": "γ"
  },
  {
    "id": 38,
    "category": "Διοίκηση Επιχειρήσεων και Οργανισμών",
    "question": "Επιτυχημένος/η Προϊστάμενος/η είναι αυτός/ή που:",
    "options": {
      "α": "Παραμένει ψύχραιμος/η υπό συνθήκες πίεσης",
      "β": "Αφιερώνει χρόνο για να μάθουν οι υφιστάμενοί του/της",
      "γ": "Προγραμματίζει και αναπληροφορείται",
      "δ": "Όλες οι λοιπές απαντήσεις"
    },
    "correct_answer": "δ"
  },
  {
    "id": 39,
    "category": "Διοίκηση Επιχειρήσεων και Οργανισμών",
    "question": "Τι από τα παρακάτω αποτελεί πρόκληση για ένα σύγχρονο διοικητικό στέλεχος:",
    "options": {
      "α": "Η διαχείριση της αλλαγής",
      "β": "Η διαχείριση της μάθησης",
      "γ": "Η διαχείριση της επικοινωνίας",
      "δ": "Όλες οι λοιπές απαντήσεις"
    },
    "correct_answer": "δ"
  },
  {
    "id": 40,
    "category": "Διοίκηση Επιχειρήσεων και Οργανισμών",
    "question": "Ο/Η μάνατζερ – προιστάμενος/η κυρίως:",
    "options": {
      "α": "Αναδεικνύεται",
      "β": "Περνά όραμα, εμπνέει, πείθει",
      "γ": "Δίνει οδηγίες, εντολές, ανταμοιβές, τιμωρίες",
      "δ": "Κερδίζει εμπιστοσύνη"
    },
    "correct_answer": "γ"
  },
  {
    "id": 41,
    "category": "Διοίκηση Επιχειρήσεων και Οργανισμών",
    "question": "Ο/Η Ηγέτης κυρίως:",
    "options": {
      "α": "Κινείται σε προκαθορισμένα τυπικά πλαίσια",
      "β": "Δέχεται και διαχειρίζεται την κατεστημένη κατάσταση",
      "γ": "Έχει μακροπρόθεσμη προοπτική",
      "δ": "Δίνει έμφαση στις διαδικασίες"
    },
    "correct_answer": "γ"
  },
  {
    "id": 42,
    "category": "Διοίκηση Επιχειρήσεων και Οργανισμών",
    "question": "Τα στυλ ηγεσίας σύμφωνα με τον R. Likert είναι:",
    "options": {
      "α": "Το αυταρχικό, το συμβουλευτικό, το εξουσιοδοτικό και το δημοκρατικό",
      "β": "Το αυταρχικό εκμεταλλευτικό, το καλοπροαίρετο αυταρχικό, το συμβουλευτικό και το συμμετοχικό",
      "γ": "Το αυταρχικό, το συμβουλευτικό και το συμμετοχικό",
      "δ": "Το προσανατολισμένο προς τα καθήκοντα και το προσανατολισμένο προς τους ανθρώπους"
    },
    "correct_answer": "β"
  },
  {
    "id": 43,
    "category": "Διοίκηση Επιχειρήσεων και Οργανισμών",
    "question": "Τα μέλη μιας ομάδας με δημοκρατικό στυλ ηγέτη, σύμφωνα με την έρευνα του τρόπου συμπεριφοράς του ηγέτη ως προς την ομάδα από τους R. Lippitt και R. White:",
    "options": {
      "α": "Δέχονται νέες ιδέες και αλλαγές",
      "β": "Δείχνουν μικρό ενδιαφέρον για τη δουλειά",
      "γ": "Εκτελούν τις εντολές χωρίς να αναλαμβάνουν ευθύνη για τα αποτελέσματα",
      "δ": "Έχουν χαμηλή απόδοση"
    },
    "correct_answer": "α"
  },
  {
    "id": 44,
    "category": "Διοίκηση Επιχειρήσεων και Οργανισμών",
    "question": "Ο/Η ηγέτης με εξουσιοδοτικό στυλ, σύμφωνα με την έρευνα του τρόπου συμπεριφοράς του ηγέτη ως προς την ομάδα από τους R. Lippitt και R. White:",
    "options": {
      "α": "Δεν έχει εμπιστοσύνη στην ηγετική του/της ικανότητα",
      "β": "Δεν χαίρει εμπιστοσύνης από τα μέλη της ομάδας",
      "γ": "Λαμβάνει αποφάσεις με συμμετοχή της ομάδας",
      "δ": "Θέτει στόχους για την ομάδα"
    },
    "correct_answer": "δ"
  },
  {
    "id": 45,
    "category": "Διοίκηση Επιχειρήσεων και Οργανισμών",
    "question": "Σύμφωνα με τον J. Kotter, ποια είναι η βασική διαφορά μεταξύ μάνατζμεντ και ηγεσίας;",
    "options": {
      "α": "Το μάνατζμεντ εστιάζει στην αλλαγή, ενώ η ηγεσία στη σταθερότητα",
      "β": "Η ηγεσία σχετίζεται με τον έλεγχο και το μάνατζμεντ με το όραμα",
      "γ": "Το μάνατζμεντ αντιμετωπίζει την πολυπλοκότητα, ενώ η ηγεσία την αλλαγή",
      "δ": "Η ηγεσία αφορά μόνο ανώτατα στελέχη"
    },
    "correct_answer": "γ"
  },
  {
    "id": 46,
    "category": "Διοίκηση Επιχειρήσεων και Οργανισμών",
    "question": "Στο μοντέλο ηγεσίας του Κ. Blanchard (Situational Leadership), ποιος παράγοντας καθορίζει κυρίως το κατάλληλο στυλ ηγεσίας;",
    "options": {
      "α": "Η προσωπικότητα ηγέτη- προϊστάμενου/ης",
      "β": "Το οργανωσιακό και επιχειρησιακό περιβάλλον",
      "γ": "Το επίπεδο ωριμότητας/ετοιμότητας των υφισταμένων",
      "δ": "Η στρατηγική της επιχείρησης ή του οργανισμού"
    },
    "correct_answer": "γ"
  },
  {
    "id": 47,
    "category": "Διοίκηση Επιχειρήσεων και Οργανισμών",
    "question": "Στη σύγχρονη διοικητική επιστήμη η ηγεσία ορίζεται κυρίως ως:",
    "options": {
      "α": "Η ιδιότητα που διαθέτουν λίγα χαρισματικά άτομα",
      "β": "Η θέση εξουσίας σε έναν οργανισμό",
      "γ": "Η διαδικασία επιρροής προς επίτευξη κοινών στόχων",
      "δ": "Το σύνολο των διοικητικών πρακτικών"
    },
    "correct_answer": "γ"
  },
  {
    "id": 48,
    "category": "Διοίκηση Επιχειρήσεων και Οργανισμών",
    "question": "Ποιο στυλ ηγεσίας του Κ. Blanchard είναι κατάλληλο για εργαζόμενους/ες υψηλής ικανότητας και δέσμευσης;",
    "options": {
      "α": "Delegating (Εξουσιοδοτεί)",
      "β": "Coaching (Πείθει)",
      "γ": "Supporting (Ζητάει συμμετοχή)",
      "δ": "Directing (Διατάσσει)"
    },
    "correct_answer": "α"
  },
  {
    "id": 49,
    "category": "Διοίκηση Επιχειρήσεων και Οργανισμών",
    "question": "Η αποτελεσματική ηγεσία:",
    "options": {
      "α": "Είναι αυστηρή και δεν μεταβάλλεται διαχρονικά",
      "β": "Συνδυάζει πολλαπλούς ρόλους, αναλόγως των δεδομένων του περιβάλλοντος",
      "γ": "Τοποθετεί τις ανάγκες του ανθρώπινου δυναμικού πάνω από αυτές του/της Προϊσταμένου/ης",
      "δ": "Δεν αποκλίνει από τις προδιαγεγραμμένες διαδικασίες και σπανίως επιχειρεί αλλαγές"
    },
    "correct_answer": "β"
  },
  {
    "id": 50,
    "category": "Διοίκηση Επιχειρήσεων και Οργανισμών",
    "question": "Σημειώστε ποιο από τα παρακάτω ΔΕΝ αποτελεί χαρακτηριστικό του ποιοτικού στυλ διοίκησης:",
    "options": {
      "α": "Η διά βίου επιμόρφωση των εργαζομένων",
      "β": "Το συμμετοχικό στυλ διοίκησης",
      "γ": "Οι κύκλοι ποιότητας",
      "δ": "Η ατομική λήψη των αποφάσεων"
    },
    "correct_answer": "δ"
  },
  {
    "id": 51,
    "category": "Διοίκηση Επιχειρήσεων και Οργανισμών",
    "question": "Ποιο χαρακτηριστικό αποδίδει ακριβέστερα τη μετασχηματιστική ηγεσία;",
    "options": {
      "α": "Η ρύθμιση απόδοσης μέσω ανταμοιβών και κυρώσεων",
      "β": "Η έμφαση στη σταθερότητα και τις καθιερωμένες διαδικασίες",
      "γ": "Ο επαναπροσδιορισμός αξιών και η δέσμευση σε κοινό όραμα",
      "δ": "Η άσκηση ηγεσίας βάσει τυπικής θέσης εξουσίας"
    },
    "correct_answer": "γ"
  },
  {
    "id": 52,
    "category": "Διοίκηση Επιχειρήσεων και Οργανισμών",
    "question": "Σύμφωνα με τον Κ. Blanchard, η ηγεσία:",
    "options": {
      "α": "Αποτελεί έμφυτο προσωπικό χαρακτηριστικό",
      "β": "Αναπτύσσεται μέσω μάθησης και εμπειρίας",
      "γ": "Περιορίζεται σε διοικητικές λειτουργίες",
      "δ": "Ασκείται κυρίως μέσω θεσμικής εξουσίας"
    },
    "correct_answer": "β"
  },
  {
    "id": 53,
    "category": "Διοίκηση Επιχειρήσεων και Οργανισμών",
    "question": "ΔΕΝ αποτελεί βασική διάσταση της συναισθηματικής νοημοσύνης:",
    "options": {
      "α": "Η αυτο-επίγνωση",
      "β": "Ο αυτο-έλεγχος",
      "γ": "Η συνεχής μάθηση",
      "δ": "Η ενσυναίσθηση"
    },
    "correct_answer": "γ"
  },
  {
    "id": 54,
    "category": "Διοίκηση Επιχειρήσεων και Οργανισμών",
    "question": "Η αποτελεσματικότητα του δημόσιου τομέα μπορεί να βελτιωθεί όταν πραγματοποιηθούν αλλαγές:",
    "options": {
      "α": "Στον τρόπο σκέψης",
      "β": "Στη νοοτροπία",
      "γ": "Στη στρατηγική",
      "δ": "Σε όλες τις λοιπές απαντήσεις"
    },
    "correct_answer": "δ"
  },
  {
    "id": 55,
    "category": "Διοίκηση Επιχειρήσεων και Οργανισμών",
    "question": "Ένας εξωτερικός παράγοντας που είναι πιθανόν να οδηγήσει έναν σύγχρονο οργανισμό σε επιχειρησιακές αλλαγές είναι:",
    "options": {
      "α": "Το επίπεδο εξειδίκευσης των υπαλλήλων",
      "β": "Οι αξίες του οργανισμού",
      "γ": "Οι πιέσεις των πολιτών",
      "δ": "Ο τεχνολογικός εξοπλισμός που επηρεάζει τη λειτουργία του προσωπικού"
    },
    "correct_answer": "γ"
  },
  {
    "id": 56,
    "category": "Διοίκηση Επιχειρήσεων και Οργανισμών",
    "question": "Η αναγκαιότητα για μεγάλης κλίμακας αλλαγές (ανασχεδιασμός διαδικασιών, έμφαση σε προγράμματα ενίσχυσης της ποιότητας, συγχωνεύσεις, κ.ά.) οφείλονται σε διάφορους λόγους, ένας εκ των οποίων αναφέρεται παρακάτω:",
    "options": {
      "α": "Οι πολεμικές συγκρούσεις",
      "β": "Η ραγδαία ανάπτυξη και εξέλιξη της τεχνολογίας, κυρίως στον τομέα των επικοινωνιών, των μεταφορών και των δικτύων πληροφοριών",
      "γ": "Οι ραγδαίες εξελίξεις στον κλάδο της ενέργειας",
      "δ": "Οι αυξήσεις στις τιμές των παρεχόμενων υπηρεσιών"
    },
    "correct_answer": "β"
  },
  {
    "id": 57,
    "category": "Διοίκηση Επιχειρήσεων και Οργανισμών",
    "question": "Ποια από τις παρακάτω μεθόδους ΔΕΝ χρησιμοποιείται για την αντιμετώπιση των αντιστάσεων των υπαλλήλων στην αλλαγή;",
    "options": {
      "α": "Η επικοινωνία με τους/τις υπαλλήλους",
      "β": "Η χειραγώγηση των αντιδρώντων",
      "γ": "Η πρόσληψη νέων υπαλλήλων",
      "δ": "Η διαπραγμάτευση με τους/τις υπαλλήλους"
    },
    "correct_answer": "γ"
  },
  {
    "id": 58,
    "category": "Διοίκηση Επιχειρήσεων και Οργανισμών",
    "question": "Οι οργανισμοί που ΔΕΝ αλλάζουν για να προσαρμοστούν στις αλλαγές του περιβάλλοντος:",
    "options": {
      "α": "Δεν αντιμετωπίζουν πρόβλημα",
      "β": "Δεν επιβιώνουν",
      "γ": "Ονομάζονται παραδοσιακοί",
      "δ": "Αντιμετωπίζονται με καχυποψία"
    },
    "correct_answer": "β"
  },
  {
    "id": 59,
    "category": "Διοίκηση Επιχειρήσεων και Οργανισμών",
    "question": "Αναφέρονται συγκεκριμένα βήματα τα οποία πρέπει να ακολουθήσουν τα στελέχη, ώστε οι εργαζόμενοι/ες να αποδεχθούν ευκολότερα τις αλλαγές. Ένα από αυτά είναι:",
    "options": {
      "α": "Η δημιουργία ομάδων εργαζομένων που θα πείσουν τους/τις συναδέλφους/ίσσες τους για την αναγκαιότητα των αλλαγών",
      "β": "Η πίεση από την πολιτική ηγεσία",
      "γ": "Οι οικονομικές κρίσεις",
      "δ": "Η άμεση λήψη αποφάσεων"
    },
    "correct_answer": "α"
  },
  {
    "id": 60,
    "category": "Διοίκηση Επιχειρήσεων και Οργανισμών",
    "question": "Ποια από τις παρακάτω μεθόδους ΔΕΝ χρησιμοποιείται για την αντιμετώπιση των αντιστάσεων στην αλλαγή;",
    "options": {
      "α": "Η εκπαίδευση προσωπικού",
      "β": "Η συμμετοχή των εργαζομένων",
      "γ": "Η άσκηση δύναμης επί των υπαλλήλων",
      "δ": "Η αξιολόγηση προσωπικού"
    },
    "correct_answer": "δ"
  },
  {
    "id": 61,
    "category": "Διοίκηση Επιχειρήσεων και Οργανισμών",
    "question": "Η υλοποίηση της αλλαγής μπορεί να ακολουθήσει τη συμμετοχική ή την αυταρχική πορεία σύμφωνα με:",
    "options": {
      "α": "Το εννοιολογικό πλαίσιο του Κ. Blanchard",
      "β": "Το μοντέλο του J. Kotter",
      "γ": "Το μοντέλο των Κ. Lewin- E. Schein",
      "δ": "Το μοντέλο των Lippit, Watson και Westley"
    },
    "correct_answer": "δ"
  },
  {
    "id": 62,
    "category": "Διοίκηση Επιχειρήσεων και Οργανισμών",
    "question": "Ποιο μοντέλο προτείνει τη διαμόρφωση οράματος και στρατηγικής για την υλοποίηση μιας οργανωσιακής αλλαγής;",
    "options": {
      "α": "Το μοντέλο των Κ. Lewin- E. Schein",
      "β": "Το μοντέλο του Κ. Blanchard",
      "γ": "Το μοντέλο του J. Kotter",
      "δ": "Το μοντέλο των R. Lippit, J. Watson και B. Westley"
    },
    "correct_answer": "γ"
  },
  {
    "id": 63,
    "category": "Διοίκηση Επιχειρήσεων και Οργανισμών",
    "question": "Σύμφωνα με το μοντέλο Κ. Lewin-E.Schein κάθε αλλαγή υλοποιείται μέσω των κάτωθι σταδίων:",
    "options": {
      "α": "Ξεπάγωμα – Αλλαγή – Ξαναπάγωμα",
      "β": "Ξεπάγωμα – Αλλαγή",
      "γ": "Αλλαγή – Πάγωμα",
      "δ": "Ξεπάγωμα – Αλλαγή – Πάγωμα"
    },
    "correct_answer": "α"
  },
  {
    "id": 64,
    "category": "Διοίκηση Επιχειρήσεων και Οργανισμών",
    "question": "ΔΕΝ αποτελεί βασική προϋπόθεση επιτυχίας μιας αλλαγής:",
    "options": {
      "α": "Η εξασφάλιση της υποστήριξης των κέντρων ισχύος",
      "β": "Η αντιμετώπιση των αντιστάσεων",
      "γ": "Η συστημική προσέγγιση",
      "δ": "Η βελτίωση της εξωστρέφειας της οργάνωσης"
    },
    "correct_answer": "δ"
  },
  {
    "id": 65,
    "category": "Διοίκηση Επιχειρήσεων και Οργανισμών",
    "question": "Στη θεωρία της οργανωσιακής αλλαγής του J. Kotter, ποιο είναι το ΠΡΩΤΟ στάδιο;",
    "options": {
      "α": "Η διαμόρφωση σαφούς στρατηγικού οράματος",
      "β": "Η συγκρότηση ισχυρής καθοδηγητικής ομάδας",
      "γ": "Η δημιουργία αίσθησης επείγοντος",
      "δ": "Η θεσμοθέτηση νέων προσεγγίσεων στην κουλτούρα"
    },
    "correct_answer": "γ"
  },
  {
    "id": 66,
    "category": "Διοίκηση Επιχειρήσεων και Οργανισμών",
    "question": "Στη διοίκηση αλλαγών, ο όρος «οργανωσιακή αδράνεια» αναφέρεται κυρίως:",
    "options": {
      "α": "Στην ταχεία προσαρμογή του οργανισμού σε νέες συνθήκες",
      "β": "Στην παθητική διατήρηση υφιστάμενων δομών και πρακτικών",
      "γ": "Στην έλλειψη ηγεσίας κατά την εφαρμογή αλλαγών",
      "δ": "Στην ανεπάρκεια οικονομικών ή ανθρώπινων πόρων"
    },
    "correct_answer": "β"
  },
  {
    "id": 67,
    "category": "Διοίκηση Επιχειρήσεων και Οργανισμών",
    "question": "Τι χαρακτηρίζει τη διοίκηση αλλαγών στον δημόσιο τομέα;",
    "options": {
      "α": "Η ταχύτητα εφαρμογής και υλοποίησης",
      "β": "Η αντίσταση των υπαλλήλων και η ανάγκη συναίνεσης",
      "γ": "Η έλλειψη κανόνων και διαδικασιών",
      "δ": "Η πλήρης ευελιξία"
    },
    "correct_answer": "β"
  },
  {
    "id": 68,
    "category": "Διοίκηση Επιχειρήσεων και Οργανισμών",
    "question": "Στη διοίκηση αλλαγών στον δημόσιο τομέα, ποιο από τα παρακάτω θεωρείται θεμελιώδες για τη βιωσιμότητα των μεταρρυθμίσεων;",
    "options": {
      "α": "Η ταχεία εφαρμογή των μέτρων",
      "β": "Ο κεντρικός έλεγχος των αποφάσεων",
      "γ": "Η περιορισμένη εμπλοκή των ενδιαφερομένων",
      "δ": "Η συμμετοχή του ανθρώπινου δυναμικού και η διαβούλευση"
    },
    "correct_answer": "δ"
  },
  {
    "id": 69,
    "category": "Διοίκηση Επιχειρήσεων και Οργανισμών",
    "question": "Ποιο στοιχείο είναι κρίσιμο στη φάση «επικοινωνίας του οράματος» κατά τον J. Kotter;",
    "options": {
      "α": "Η λεπτομερής τεκμηρίωση",
      "β": "Η τυπική ανακοίνωση από τη διοίκηση",
      "γ": "Η συνέπεια λόγων και πράξεων της ηγεσίας",
      "δ": "Η ιεραρχική επιβολή"
    },
    "correct_answer": "γ"
  },
  {
    "id": 70,
    "category": "Διοίκηση Επιχειρήσεων και Οργανισμών",
    "question": "Ποια από τις παρακάτω προτάσεις είναι ορθή για τη διαδικασία αλλαγής της κουλτούρας ενός οργανισμού;",
    "options": {
      "α": "Μπορεί να επιτευχθεί μέσα σε λίγες ημέρες",
      "β": "Δεν απαιτείται συμμετοχή μεγάλου αριθμού στελεχών και εργαζομένων",
      "γ": "Απαιτείται η υποστήριξη από την ανώτατη διοίκηση",
      "δ": "Ο επιθυμητή κουλτούρα δεν είναι απαραίτητο να ευθυγραμμίζεται με την αποστολή, το περιβάλλον και την εταιρική στρατηγική"
    },
    "correct_answer": "γ"
  },
  {
    "id": 71,
    "category": "Διοίκηση Επιχειρήσεων και Οργανισμών",
    "question": "Τι από τα παρακάτω ΔΕΝ ισχύει για την οργανωσιακή κουλτούρα:",
    "options": {
      "α": "Άρχισε να απασχολεί θεωρητικούς και στελέχη μετά το 1995",
      "β": "Αποτελεί το «ποιόν» ενός οργανισμού",
      "γ": "Αποτελεί πηγή ανταγωνιστικών πλεονεκτημάτων",
      "δ": "Απασχόλησε την ακαδημαική κοινότητα τη δεκαετία του 1980"
    },
    "correct_answer": "α"
  },
  {
    "id": 72,
    "category": "Διοίκηση Επιχειρήσεων και Οργανισμών",
    "question": "Ποια από τις παρακάτω ενέργειες διεξάγονται στο στάδιο της διάδοσης της επιθυμητής κουλτούρας;",
    "options": {
      "α": "Οι προσλήψεις του προσωπικού",
      "β": "Η αξιολόγηση των υπαλλήλων",
      "γ": "Η εκπαίδευση των υπαλλήλων",
      "δ": "Η μείωση του προσωπικού"
    },
    "correct_answer": "γ"
  },
  {
    "id": 73,
    "category": "Διοίκηση Επιχειρήσεων και Οργανισμών",
    "question": "Η οργανωσιακή κουλτούρα:",
    "options": {
      "α": "Διαμορφώνεται κυρίως μέσω τυπικών κανονισμών και γραπτών διαδικασιών",
      "β": "Αναπτύσσεται μέσα από κοινές αξίες, πρότυπα συμπεριφοράς και άτυπες πρακτικές",
      "γ": "Επηρεάζεται αποκλειστικά από το στυλ ηγεσίας της ανώτατης διοίκησης",
      "δ": "Λειτουργεί ανεξάρτητα από τα κίνητρα και τις αντιλήψεις των εργαζομένων"
    },
    "correct_answer": "β"
  },
  {
    "id": 74,
    "category": "Διοίκηση Επιχειρήσεων και Οργανισμών",
    "question": "Ποια από τις παρακάτω επιλογές στην τυπολογία των R. Harrison και C. Handy είναι ορθή;",
    "options": {
      "α": "Ο Δίας συνδέεται με τη δύναμη",
      "β": "Ο Απόλλων συνδέεται με το καθήκον",
      "γ": "Η Αθηνά συνδέεται με το άτομο",
      "δ": "Ο Διόνυσος συνδέεται με τον ρόλο"
    },
    "correct_answer": "α"
  },
  {
    "id": 75,
    "category": "Διοίκηση Επιχειρήσεων και Οργανισμών",
    "question": "Σύμφωνα με τον G. Hofstede, υψηλή αποφυγή αβεβαιότητας ενός οργανισμού σημαίνει:",
    "options": {
      "α": "Έμφαση σε κανόνες και διαδικασίες",
      "β": "Ανοχή στον κίνδυνο",
      "γ": "Καινοτομία χωρίς περιορισμούς",
      "δ": "Ευελιξία ρόλων"
    },
    "correct_answer": "α"
  },
  {
    "id": 76,
    "category": "Διοίκηση Επιχειρήσεων και Οργανισμών",
    "question": "Ποιος συνδυασμός διαστάσεων οργανωσιακής κουλτούρας κατά τον G. Hofstede περιγράφει καλύτερα το περιβάλλον στο οποίο οι υπάλληλοι αποδέχονται πλήρως την ιεραρχία, αποφεύγουν τη διαφωνία με προϊστάμενους/ες και προτιμούν αυστηρούς κανόνες;",
    "options": {
      "α": "Χαμηλή απόσταση από την εξουσία και χαμηλή αποφυγή αβεβαιότητας",
      "β": "Υψηλή συλλογικότητα και χαμηλή αρενωπότητα",
      "γ": "Υψηλή απόσταση από την εξουσία και υψηλή αποφυγή αβεβαιότητας",
      "δ": "Υψηλός ατομικισμός και μακροπρόθεσμος προσανατολισμός"
    },
    "correct_answer": "γ"
  },
  {
    "id": 77,
    "category": "Διοίκηση Επιχειρήσεων και Οργανισμών",
    "question": "Η οριζόντια επικοινωνία:",
    "options": {
      "α": "Δεν βοηθάει στη βελτίωση της συνεργασίας στο τμήμα ή τη διεύθυνση",
      "β": "Ξεκινάει από τα κατώτερα και καταλήγει στα ανώτερα ιεραρχικά επίπεδα",
      "γ": "Πραγματοποιείται μεταξύ υπαλλήλων σε διαφορετικά τμήματα του οργανισμού",
      "δ": "Ξεκινάει από τα ανώτερα και καταλήγει στα κατώτερα ιεραρχικά επίπεδα"
    },
    "correct_answer": "γ"
  },
  {
    "id": 78,
    "category": "Διοίκηση Επιχειρήσεων και Οργανισμών",
    "question": "Η γραπτή επικοινωνία είναι περισσότερο αποτελεσματική:",
    "options": {
      "α": "Για πληροφορίες που αφορούν μελλοντική δράση των υπαλλήλων",
      "β": "Για πληροφορίες που αφορούν άμεση δράση των υπαλλήλων",
      "γ": "Για επίλυση παρεξηγήσεων του προσωπικού",
      "δ": "Για επίπληξη των υπαλλήλων"
    },
    "correct_answer": "α"
  },
  {
    "id": 79,
    "category": "Διοίκηση Επιχειρήσεων και Οργανισμών",
    "question": "Η προφορική επικοινωνία είναι περισσότερο αποτελεσματική:",
    "options": {
      "α": "Για πληροφορίες που αφορούν μελλοντική δράση των υπαλλήλων",
      "β": "Για λύση προβλημάτων και διαφορών μεταξύ υπαλλήλων",
      "γ": "Για πληροφορίες γενικής φύσης",
      "δ": "Για οδηγίες ή εντολές στους/στις υπαλλήλους"
    },
    "correct_answer": "β"
  },
  {
    "id": 80,
    "category": "Διοίκηση Επιχειρήσεων και Οργανισμών",
    "question": "Η άτυπη επικοινωνία:",
    "options": {
      "α": "Ξεκινάει από τα ανώτερα και καταλήγει στα κατώτερα ιεραρχικά επίπεδα",
      "β": "Ξεκινάει από τα κατώτερα και καταλήγει στα ανώτερα ιεραρχικά επίπεδα",
      "γ": "Πραγματοποιείται μεταξύ υπαλλήλων σε διαφορετικά τμήματα του οργανισμού",
      "δ": "Πραγματοποιείται μεταξύ των υπαλλήλων έξω από τις επίσημες δομές και διαδικασίες"
    },
    "correct_answer": "δ"
  },
  {
    "id": 81,
    "category": "Διοίκηση Επιχειρήσεων και Οργανισμών",
    "question": "Παράγοντες που ευχαριστούν/παρακινούν τους υπαλλήλους κατά τον F. Herzberg είναι:",
    "options": {
      "α": "Η πολιτική του οργανισμού",
      "β": "Οι διαπροσωπικές σχέσεις",
      "γ": "Η ασφάλεια της απασχόλησης",
      "δ": "Η δυνατότητα επαγγελματικής ανάπτυξης"
    },
    "correct_answer": "δ"
  },
  {
    "id": 82,
    "category": "Διοίκηση Επιχειρήσεων και Οργανισμών",
    "question": "Παράγοντες που δυσαρεστούν τους υπαλλήλους κατά τον F. Herzberg είναι:",
    "options": {
      "α": "Τα επιτεύγματα",
      "β": "Οι συνθήκες εργασίας",
      "γ": "Η αναγνώριση από τη Διοίκηση",
      "δ": "Η εξέλιξη στην ιεραρχία"
    },
    "correct_answer": "β"
  },
  {
    "id": 83,
    "category": "Διοίκηση Επιχειρήσεων και Οργανισμών",
    "question": "Σύμφωνα με τη θεωρία «των προσδοκιών» του V. Vroom:",
    "options": {
      "α": "Αν το άτομο πιστεύει ότι αν προσπαθήσει θα αποδώσει, και αν αποδώσει θα ανταμειφθεί ανάλογα, τότε η προσδοκία είναι θετική και αυξάνει τη διάθεση του ατόμου για απόδοση",
      "β": "Ο/Η υπάλληλος συγκρίνει αυτά που συνεισφέρει στον οργανισμό με αυτά που απολαμβάνει και προσδοκά την ανταμοιβή του/της",
      "γ": "Ο/Η υπάλληλος συγκρίνει τη δική του σχέση προσφορών/απολαβών με τις αντίστοιχες σχέσεις άλλων υπαλλήλων μέσα και έξω από τον οργανισμό",
      "δ": "Κανένα από τα παραπάνω δεν ισχύει σύμφωνα με τη θεωρία «των προσδοκιών»"
    },
    "correct_answer": "α"
  },
  {
    "id": 84,
    "category": "Διοίκηση Επιχειρήσεων και Οργανισμών",
    "question": "Οι ανάγκες-κίνητρα που προσδιορίζουν την παρακίνηση του ανθρώπου σύμφωνα με τη θεωρία των επιτευγμάτων (McClelland) είναι:",
    "options": {
      "α": "Οι ανάγκες για: ασφάλεια, κοινωνικές σχέσεις και επιτεύγματα",
      "β": "Οι ανάγκες για: κοινωνικές σχέσεις, δύναμη και επιτεύγματα",
      "γ": "Οι ανάγκες για: κοινωνικές σχέσεις, αυτοπραγμάτωση και αναγνώριση",
      "δ": "Οι φυσιολογικές ανάγκες και οι ανάγκες για: κοινωνικότητα, ασφάλεια και επιτεύγματα"
    },
    "correct_answer": "β"
  },
  {
    "id": 85,
    "category": "Διοίκηση Επιχειρήσεων και Οργανισμών",
    "question": "Ένας ρόλος των μελών της ομάδας που συμβάλλει στη συνοχή και αποτελεσματική λειτουργία της ομάδας είναι:",
    "options": {
      "α": "Η ανάπτυξη πρωτοβουλιών",
      "β": "Η αναζήτηση πληροφοριών",
      "γ": "Ο καθορισμός διαδικασιών και κανόνων",
      "δ": "Η παροχή πληροφοριών"
    },
    "correct_answer": "γ"
  },
  {
    "id": 86,
    "category": "Διοίκηση Επιχειρήσεων και Οργανισμών",
    "question": "Η συμπεριφορά των μελών της ομάδας που κυρίως συμβάλλει στη συνοχή της ομάδας είναι:",
    "options": {
      "α": "Η αντιμετώπιση αρνητικών, αντι-ομαδικών συμπεριφορών",
      "β": "Η αποτελεσματική υλοποίηση του έργου",
      "γ": "Η ανάληψη πρωτοβουλιών",
      "δ": "Η εξεύρεση λύσεων"
    },
    "correct_answer": "α"
  },
  {
    "id": 87,
    "category": "Διοίκηση Επιχειρήσεων και Οργανισμών",
    "question": "Οι ομαδικές αποφάσεις είναι προτιμότερες σε σχέση με τις ατομικές:",
    "options": {
      "α": "Όταν το άτομο στερείται πληροφοριών ή εξειδίκευσης",
      "β": "Το πρόβλημα είναι σαφές και εύκολο να προσδιοριστεί",
      "γ": "Δεν απαιτείται αποδοχή από τα άλλα μέλη για αποτελεσματική εφαρμογή",
      "δ": "Δεν υπάρχει αρκετός χρόνος για συλλογική δράση"
    },
    "correct_answer": "α"
  },
  {
    "id": 88,
    "category": "Διοίκηση Επιχειρήσεων και Οργανισμών",
    "question": "ΔΕΝ αποτελεί χαρακτηριστικό των αποτελεσματικών ομάδων:",
    "options": {
      "α": "Η άνετη, ανεπίσημη ατμόσφαιρα",
      "β": "Η έλλειψη αφοσίωσης και υπευθυνότητας των μελών",
      "γ": "Η εναρμόνιση ατομικών και ομαδικών στόχων",
      "δ": "Η ικανοποίηση και παρακίνηση των μελών"
    },
    "correct_answer": "β"
  },
  {
    "id": 89,
    "category": "Διοίκηση Επιχειρήσεων και Οργανισμών",
    "question": "Ποιο από τα παρακάτω αποτελεί χαρακτηριστικό της οργάνωσης που μαθαίνει;",
    "options": {
      "α": "Η έλλειψη οργανωσιακής μνήμης",
      "β": "Ο ανταγωνισμός",
      "γ": "Ο πειραματισμός",
      "δ": "Η τιμωρία των αποτυχιών και των λαθών"
    },
    "correct_answer": "γ"
  },
  {
    "id": 90,
    "category": "Διοίκηση Επιχειρήσεων και Οργανισμών",
    "question": "Ένα εργαλείο δεύτερης γενιάς για την υποστήριξη της οργανωσιακής μάθησης είναι:",
    "options": {
      "α": "Τα συστήματα προτάσεων εργαζομένων",
      "β": "Οι κύκλοι ποιότητας",
      "γ": "Τα συστήματα διοίκησης της γνώσης (knowledge management)",
      "δ": "Ο επανασχεδιασμός των επιχειρησιακών διαδικασιών"
    },
    "correct_answer": "γ"
  },
  {
    "id": 91,
    "category": "Διοίκηση Επιχειρήσεων και Οργανισμών",
    "question": "Τι είναι η οργανωσιακή μάθηση;",
    "options": {
      "α": "Η συλλογική βελτίωση μέσω εμπειρίας και γνώσης",
      "β": "Η εκπαίδευση του προσωπικού",
      "γ": "Η γνώση του οργανογράμματος της υπηρεσίας",
      "δ": "Η τυπική συμμόρφωση με τους κανόνες του οργανισμού"
    },
    "correct_answer": "α"
  },
  {
    "id": 92,
    "category": "Διοίκηση Επιχειρήσεων και Οργανισμών",
    "question": "Σύμφωνα με τον Ρ. Senge ποια από τις παρακάτω αρχές ΔΕΝ συμβάλλει στην οργανωσιακή μάθηση;",
    "options": {
      "α": "Η ατομική μάθηση",
      "β": "Τα νοητικά μοντέλα",
      "γ": "Η συστημική σκέψη",
      "δ": "Το κοινό όραμα"
    },
    "correct_answer": "α"
  },
  {
    "id": 93,
    "category": "Διοίκηση Επιχειρήσεων και Οργανισμών",
    "question": "Σύμφωνα με τον Ρ. Senge ένας από τους ρόλους που πρέπει να παίζουν με επιτυχία οι ηγέτες για να χτίσουν τις μαθησιακές οργανώσεις είναι:",
    "options": {
      "α": "Ο ρόλος του/της Πολιτικού Μηχανικού",
      "β": "Ο ρόλος του/της καθηγητή/τριας",
      "γ": "Ο ρόλος του/της υπηρέτη/υπηρέτριας",
      "δ": "Ο ρόλος του/της δικηγόρου"
    },
    "correct_answer": "γ"
  },
  {
    "id": 94,
    "category": "Διοίκηση Επιχειρήσεων και Οργανισμών",
    "question": "Ποια είναι η βασική λειτουργία της Ισορροπημένης Κάρτας Επιδόσεων (Balanced Scorecard) που τη διαφοροποιεί από τα παραδοσιακά συστήματα μέτρησης απόδοσης;",
    "options": {
      "α": "Η αποκλειστική αξιολόγηση της οικονομικής αποδοτικότητας και αποτελεσματικότητας",
      "β": "Η παρακολούθηση της απόδοσης μέσω ανεξάρτητων μεταξύ τους δεικτών",
      "γ": "Η συνδυαστική χρήση χρηματοοικονομικών και μη χρηματοοικονομικών δεικτών",
      "δ": "Η περιοδική αποτύπωση των συνολικών αποτελεσμάτων του οργανισμού ως προς τον έλεγχο του κόστους"
    },
    "correct_answer": "γ"
  },
  {
    "id": 95,
    "category": "Διοίκηση Επιχειρήσεων και Οργανισμών",
    "question": "Ποιος είναι ο ρόλος της Συγκριτικής Αξιολόγησης (Benchmarking);",
    "options": {
      "α": "Ο εσωτερικός έλεγχος",
      "β": "Ο καθορισμός μισθών και κινήτρων",
      "γ": "Η μείωση προσωπικού και ο περιορισμός του κόστους",
      "δ": "Η προσαρμογή πρακτικών βάσει βέλτιστων προτύπων επίδοσης"
    },
    "correct_answer": "δ"
  },
  {
    "id": 96,
    "category": "Διοίκηση Επιχειρήσεων και Οργανισμών",
    "question": "Ποιο από τα παρακάτω χαρακτηρίζει τη δημιουργική ποιότητα (creative quality) και την καινοτομία αξίας (value innovation);",
    "options": {
      "α": "Η ικανοποίηση των αναγκών του πολίτη",
      "β": "Η έρευνα",
      "γ": "Η ταχύτητα μετάδοσης ιδεών",
      "δ": "Η τεχνογνωσία"
    },
    "correct_answer": "α"
  },
  {
    "id": 97,
    "category": "Διοίκηση Επιχειρήσεων και Οργανισμών",
    "question": "Ο συνδυασμός καινοτομίας και ποιότητας είναι αναγκαίος για:",
    "options": {
      "α": "Την εφαρμογή των αλλαγών στους οργανισμούς και στις υπηρεσίες",
      "β": "Την επιβίωση των οικονομικών μονάδων και τη βελτίωση της ανταγωνιστικότητας των εθνικών οικονομιών",
      "γ": "Την αποτελεσματικότητα των διαδικασιών",
      "δ": "Την επέκταση της χρήσης της σύγχρονης τεχνολογίας από τους πολίτες για την αρτιότερη εξυπηρέτηση των αιτημάτων τους"
    },
    "correct_answer": "β"
  },
  {
    "id": 98,
    "category": "Διοίκηση Επιχειρήσεων και Οργανισμών",
    "question": "Με τη φράση «εμπόδια αντίληψης για την επίτευξη της Ολικής Ποιότητας», μεταξύ των άλλων νοείται ένα από τα κατωτέρω:",
    "options": {
      "α": "Η αδυναμία θεώρησης του προβλήματος από όλες τις πλευρές του",
      "β": "Το αίσθημα, η ενόραση, η ποιοτική κρίση και η ευχαρίστηση ως στοιχεία αρνητικά",
      "γ": "Η έλλειψη συνεργασίας και εμπιστοσύνης μεταξύ συναδέλφων",
      "δ": "Ο φόβος χαρακτηρισμού των ιδεών από τους άλλους"
    },
    "correct_answer": "δ"
  },
  {
    "id": 99,
    "category": "Διοίκηση Επιχειρήσεων και Οργανισμών",
    "question": "Οι φορείς του δημοσίου τομέα που θέλουν να πιστοποιηθούν για την ορθή και ολοκληρωμένη εφαρμογή του Κοινού Πλαισίου Αξιολόγησης (Κ.Π.Α.) καλούνται να υποβάλουν:",
    "options": {
      "α": "Έκθεση ανάλυσης κινδύνου για την εφαρμογή του Κ.Π.Α.",
      "β": "Έγγραφο έγκρισης του Κ.Π.Α. από το Υπουργείο Εσωτερικών",
      "γ": "Ανάλυση των χρηματοοικονομικών στοιχείων τους",
      "δ": "Μελέτη εφαρμογής του Κ.Π.Α και δήλωση πολιτικής ποιότητας"
    },
    "correct_answer": "δ"
  },
  {
    "id": 100,
    "category": "Διοίκηση Επιχειρήσεων και Οργανισμών",
    "question": "Σημειώστε το λάθος! Οι on line συναλλαγές των φορέων του δημόσιου τομέα σημαίνουν:",
    "options": {
      "α": "Καλύτερες σχέσεις πολίτη – κράτους",
      "β": "Αδιαφάνεια στη δημόσια διοίκηση",
      "γ": "Καλύτερη παροχή υπηρεσιών",
      "δ": "Αποτελεσματικότερη οργάνωση"
    },
    "correct_answer": "β"
  },
  {
    "id": 101,
    "category": "Διοίκηση Επιχειρήσεων και Οργανισμών",
    "question": "Ο Ανασχεδιασμός των Επιχειρησιακών Διαδικασιών (Business Process Reengineering - BPR) είναι η μεθοδολογία που:",
    "options": {
      "α": "Τονίζει την εξαρχής δημιουργία διαδικασιών και τις εκ βάθρων αλλαγές σε έναν οργανισμό",
      "β": "Αυτοματοποιεί τις επιχειρηματικές διαδικασίες",
      "γ": "Βελτιστοποιεί την ποιότητα των παρεχόμενων υπηρεσιών",
      "δ": "Ορθολογοποιεί τη ροή εργασιών σε μια μονάδα, κάνοντάς την περισσότερο αποδοτική, αποτελεσματική και ικανή να προσαρμόζεται σε ένα ραγδαία μεταβαλλόμενο εξωτερικό περιβάλλον"
    },
    "correct_answer": "δ"
  },
  {
    "id": 102,
    "category": "Διοίκηση Επιχειρήσεων και Οργανισμών",
    "question": "Η διαβούλευση επί των νομοσχεδίων γίνεται και μέσω του δικτυακού τόπου www.opengov.gr και, κατά κανόνα, διαρκεί:",
    "options": {
      "α": "Ένα (1) μήνα",
      "β": "Δύο (2) μήνες",
      "γ": "Μία (1) εβδομάδα",
      "δ": "Δύο (2) εβδομάδες"
    },
    "correct_answer": "δ"
  },
  {
    "id": 103,
    "category": "Διοίκηση Επιχειρήσεων και Οργανισμών",
    "question": "Ο όρος «εκφοβισμός στον χώρο εργασίας» (workplace bullying) σημαίνει:",
    "options": {
      "α": "Κακομεταχείριση με απειλές ή ταπείνωση, δολιοφθορά, λεκτική κακοποίηση",
      "β": "Ανθυγιεινό περιβάλλον εργασίας",
      "γ": "Προσδοκίες οι οποίες είναι δύσκολο να πραγματοποιηθούν",
      "δ": "Τραυματισμοί που προκαλούνται από παρατεταμένες, επαναλαμβανόμενες σωματικές εργασίες"
    },
    "correct_answer": "α"
  },
  {
    "id": 104,
    "category": "Διοίκηση Επιχειρήσεων και Οργανισμών",
    "question": "Το Εθνικό Σύστημα Πολυεπίπεδης Διακυβέρνησης εφαρμόζεται:",
    "options": {
      "α": "Στον στενό δημοσιο τομέα",
      "β": "Σε όλα τα νομικά πρόσωπα δημοσίου δικαίου",
      "γ": "Σε όλα τα νομικά πρόσωπα δημοσίου και ιδιωτικού δικαίου του δημόσιου τομέα",
      "δ": "Στον δημόσιο τομέα και σε όλα τα νομικά πρόσωπα ιδιωτικού δικαίου του δημόσιου τομέα"
    },
    "correct_answer": "δ"
  },
  {
    "id": 105,
    "category": "Διοίκηση Επιχειρήσεων και Οργανισμών",
    "question": "Το Εθνικό Συμβούλιο Πολυεπίπεδης Διακυβέρνησης ΔΕΝ:",
    "options": {
      "α": "Εκπονεί μελέτες και υποβάλλει προτάσεις με σκοπό την υιοθέτηση βέλτιστων διεθνών πρακτικών αποκέντρωσης, αποσυγκέντρωσης και μεταφοράς αρμοδιοτήτων",
      "β": "Σχεδιάζει πολιτικές προώθησης της εφαρμογής του Εθνικού Συστήματος Πολυεπίπεδης Διακυβέρνησης",
      "γ": "Γνωμοδοτεί κατόπιν ερωτήματος του Προέδρου του Συμβουλίου Διοίκησης της Εθνικής Αρχής Διαφάνειας",
      "δ": "Συλλέγει και παρακολουθεί τη νομολογία των εθνικών δικαστηρίων"
    },
    "correct_answer": "δ"
  },
  {
    "id": 106,
    "category": "Διοίκηση Επιχειρήσεων και Οργανισμών",
    "question": "Πρωταρχική και αναγκαία προϋπόθεση για την αναδιάρθρωση του Δημόσιου Τομέα είναι:",
    "options": {
      "α": "Η μετακίνηση του ανθρώπινου δυναμικού",
      "β": "Η μείωση του ανθρώπινου δυναμικού",
      "γ": "Η μεταφορά των διοικητικών εφαρμογών στο Διαδίκτυο",
      "δ": "Η κατάργηση δημοσίων υπηρεσιών και οργανισμών"
    },
    "correct_answer": "α"
  },
  {
    "id": 107,
    "category": "Διοίκηση Επιχειρήσεων και Οργανισμών",
    "question": "Σκοπός της αξιολόγησης των δημόσιων πολιτικών είναι να:",
    "options": {
      "α": "Προσδιοριστεί το περιεχόμενο που θα έχει η τελική απόφαση για την αντιμετώπιση ενός δημόσιου προβλήματος",
      "β": "Εκτιμηθεί σε ποιον βαθμό με την εφαρμοσθείσα δημόσια πολιτική επήλθαν τα προσδοκώμενα αποτελέσματα",
      "γ": "Διαπιστωθεί η καταλληλότητα της χρονικής συγκυρίας, ώστε να ληφθούν αποφάσεις",
      "δ": "Καθοριστεί ποιοι θα επιφορτιστούν με την εκτέλεση των αποφάσεων και την υλοποίηση της πολιτικής"
    },
    "correct_answer": "β"
  },
  {
    "id": 108,
    "category": "Διοίκηση Επιχειρήσεων και Οργανισμών",
    "question": "Η κοινωνική ευθύνη:",
    "options": {
      "α": "Αναφέρεται στους κανόνες που διέπουν τη προσωπική ζωή ενός ατόμου",
      "β": "Δίνει έμφαση σε αξίες που οφείλουν να υιοθετήσουν οι σύγχρονοι δημόσιοι οργανισμοί, όπως η αλήθεια και η δικαιοσύνη",
      "γ": "Είναι η υποχρέωση της δημόσιας οικονομικής μονάδας για επίτευξη μακροχρόνιων στόχων προς όφελος της κοινωνίας",
      "δ": "Είναι η προσπάθεια εναρμόνισης της λειτουργίας και της πολιτικής ενός δημόσιου οργανισμού με το κοινωνικό περιβάλλον, σε όρους ωφέλειας για τον ίδιο και την κοινωνία"
    },
    "correct_answer": "δ"
  }
]